py_gen_ml/__init__.py
py_gen_ml/extensions.proto
py_gen_ml/extensions_pb2.py
py_gen_ml/extensions_pb2.pyi
py_gen_ml/py.typed
py_gen_ml/cli_args/__init__.py
py_gen_ml/cli_args/arg_refs.py
py_gen_ml/cli_args/cli_func.py
py_gen_ml/cmd/__init__.py
py_gen_ml/cmd/generate.py
py_gen_ml/logging/__init__.py
py_gen_ml/logging/setup_logger.py
py_gen_ml/plugin/__init__.py
py_gen_ml/plugin/base_model_generator.py
py_gen_ml/plugin/cli_args_generator.py
py_gen_ml/plugin/common.py
py_gen_ml/plugin/constants.py
py_gen_ml/plugin/generator.py
py_gen_ml/plugin/json_schema_task_generator.py
py_gen_ml/plugin/main.py
py_gen_ml/plugin/sweep_model_generator.py
py_gen_ml/plugin/yapf_style.toml
py_gen_ml/sweep/__init__.py
py_gen_ml/sweep/sweep.py
py_gen_ml/sweep/tune/__init__.py
py_gen_ml/sweep/tune/optuna.py
py_gen_ml/typing/__init__.py
py_gen_ml/typing/some.py
py_gen_ml/yaml/__init__.py
py_gen_ml/yaml/object_path.py
py_gen_ml/yaml/yaml_model.py
py_gen_ml-0.3.0.dist-info/METADATA
py_gen_ml-0.3.0.dist-info/WHEEL
py_gen_ml-0.3.0.dist-info/entry_points.txt
py_gen_ml-0.3.0.dist-info/licenses/LICENSE
py_gen_ml-0.3.0.dist-info/RECORD
