Metadata-Version: 2.3
Name: py-gen-ml
Version: 0.3.0
Summary: A Python library for generating machine learning tooling.
Project-URL: Home, https://github.com/jostosh/py-gen-ml
Project-URL: Documentation, https://jostosh.github.io/py-gen-ml
Author-email: Jos van de Wolfshaar <jos.vandewolfshaar@gmail.com>
License: MIT License
Keywords: code generation,hyperparameter optimization,machine learning,mlops,optuna,protobufs
Classifier: Development Status :: 3 - Alpha
Classifier: Intended Audience :: Developers
Classifier: License :: OSI Approved :: MIT License
Classifier: Programming Language :: Python :: 3
Classifier: Programming Language :: Python :: 3.9
Classifier: Programming Language :: Python :: 3.10
Classifier: Programming Language :: Python :: 3.11
Classifier: Programming Language :: Python :: 3.12
Classifier: Programming Language :: Python :: 3.13
Requires-Python: >=3.9
Requires-Dist: grpcio-tools>=1.46.0
Requires-Dist: jsonmerge>=1.9.2
Requires-Dist: mkdocs-material[docs,imaging]>=9.5.39
Requires-Dist: more-itertools>=10.5.0
Requires-Dist: networkx>=3.0
Requires-Dist: numpy<2
Requires-Dist: optuna>=3.2.0
Requires-Dist: protobuf<5.28.0,>=5.0.0
Requires-Dist: protogen>=0.3.1
Requires-Dist: pydantic<3,>=2
Requires-Dist: rich>=13.8.1
Requires-Dist: ruamel-yaml>=0.17.32
Requires-Dist: typer>=0.12.5
Requires-Dist: yapf>=0.40.2
Provides-Extra: docs
Requires-Dist: mdx-truly-sane-lists>=1.3; extra == 'docs'
Requires-Dist: mkdocs-material>=9.5.39; extra == 'docs'
Requires-Dist: mkdocs-section-index>=0.3.9; extra == 'docs'
Requires-Dist: mkdocs-video>=1.5.0; extra == 'docs'
Requires-Dist: mkdocstrings[python]>=0.26.1; extra == 'docs'
Requires-Dist: pymdown-extensions>=10.11.2; extra == 'docs'
